hivisionai/__init__.py
hivisionai/app.py
hivisionai/hyService/__init__.py
hivisionai/hyService/cloudService.py
hivisionai/hyService/dbTools.py
hivisionai/hyService/error.py
hivisionai/hyService/serviceTest.py
hivisionai/hyService/utils.py
hivisionai/hyTrain/APIs.py
hivisionai/hyTrain/DataProcessing.py
hivisionai/hyTrain/__init__.py
hivisionai/hycv/__init__.py
hivisionai/hycv/error.py
hivisionai/hycv/face_tools.py
hivisionai/hycv/idphoto.py
hivisionai/hycv/matting_tools.py
hivisionai/hycv/tensor2numpy.py
hivisionai/hycv/utils.py
hivisionai/hycv/vision.py
hivisionai/hycv/FaceDetection68/__init__.py
hivisionai/hycv/FaceDetection68/faceDetection68.py
hivisionai/hycv/idphotoTool/__init__.py
hivisionai/hycv/idphotoTool/cuny_tools.py
hivisionai/hycv/idphotoTool/idphoto_change_cloth.py
hivisionai/hycv/idphotoTool/idphoto_cut.py
hivisionai/hycv/idphotoTool/move_image.py
hivisionai/hycv/idphotoTool/neck_processing.py
hivisionai/hycv/mtcnn_onnx/__init__.py
hivisionai/hycv/mtcnn_onnx/box_utils.py
hivisionai/hycv/mtcnn_onnx/detector.py
hivisionai/hycv/mtcnn_onnx/first_stage.py
hivisionai/hycv/mtcnn_onnx/visualization_utils.py
HY_sdk-0.2.56.dist-info/METADATA
HY_sdk-0.2.56.dist-info/WHEEL
HY_sdk-0.2.56.dist-info/entry_points.txt
HY_sdk-0.2.56.dist-info/top_level.txt
HY_sdk-0.2.56.dist-info/RECORD
