Metadata-Version: 2.1
Name: HY-sdk
Version: 0.2.56
Summary: HIVISION Project team's self-built package for a new project team, involving algorithm, model training and back-end deployment
Home-page: https://github.com/huanyingyixin/HY-sdk
Project-URL: Bug Tracker, https://github.com/huanyingyixin/HY-sdk/issues
Project-URL: Changelog, https://github.com/huanyingyixin/HY-sdk/releases
Classifier: Programming Language :: Python :: 3
Classifier: License :: OSI Approved :: BSD License
Classifier: Intended Audience :: Developers
Requires-Python: >=3.6
